proofutils/__init__.py
proofutils-1.0.2.dist-info/LICENSE.md
proofutils-1.0.2.dist-info/METADATA
proofutils-1.0.2.dist-info/WHEEL
proofutils-1.0.2.dist-info/top_level.txt
proofutils-1.0.2.dist-info/RECORD
