Metadata-Version: 2.1
Name: proofutils
Version: 1.0.2
Summary: ProofUtils, a swift package to generate fake gifting proofs for Discord owners.
Home-page: https://github.com/ercenterprises/ProofUtils
Author: ERC Enterprises
Author-email: heya.discordbot@gmail.com
License: LICENSE
Classifier: Development Status :: 4 - Beta
Classifier: Programming Language :: Python :: 3
Classifier: Operating System :: OS Independent
License-File: LICENSE.md
